{
    "cache": "cache.json",
    "cache_default": {
        "saved_case_info_dir": "",
        "error_patterns": ""
    },
    "restart_filter_threshold": {
        "default": 3,
        "sas-workload-orchestrator": 1,
        "sas-analytics-execution": 2
    },
    "max_files_to_show": 10,
    "mongodb_conn_var_url": "http://trck1076843.trc.sas.com:8000/.env",
    "user_activity_url": "http://trck1076843.trc.sas.com:8000/record",
    "output_timestamp_format": "%Y-%m-%d %H:%M:%S",
    "print_level": 1,
    "output_folder": "output",
    "logging": {
        "level": "INFO",
        "format": "%(asctime)s %(levelname)s %(message)s",
        "retention_days": 1,
        "file_name": "auto_k8s_info.log"
    },
    "cleaner": {
        "ip_address": true,
        "port": true,
        "job_number": true
    },
    "yes_list": [
        "yes",
        "y",
        "Y",
        "Yes",
        "",
        "YES"
    ],
    "invalid_windows_path_chars": [
        "<",
        ">",
        "\"",
        "/",
        "|",
        "?",
        "*"
    ],
    "describe_pods_error_patterns": {
        "Warning": [
            "Warning"
        ],
        "Reason": [
            "OOMKilled",
            "OutOfcpu",
            "Error"
        ],
        "Pod rejected": [
            "Pod was rejected: Node didn't have enough resource:"
        ]
    },
    "get_pods_error_patterns": {
        "Error": [
            "Error"
        ],
        "Running No Pods": [
            "0/",
            "Running"
        ],
        "Out of CPU": [
            "OutOfcpu"
        ],
        "Hanged in Init": [
            "Init:"
        ],
        "Crashed": [
            "CrashLoopBackOff"
        ]
    },
    "log_error_patterns": {
        "CAS Control Issues": [
            "no ready CAS servers",
            "cas-control is not ready",
            "Unable to lookup CAS server cas-gp-default.  Response code 404 received",
            "Deleting failed ControllerPod"
        ],
        "CAS Worker Issues": [
            "TKCASTAB_GENERIC_TKIOE_FAIL"
        ],
        "Readiness Check Failures": [
            "check \"sas-endpoints-ready\" failed",
            "no available addresses",
            "endpoints have no available addresses",
            "0 available addresses",
            "failed readiness check"
        ],
        "Authentication Failures": [
            "Unauthorized",
            "authentication failed",
            "access denied",
            "invalid credentials",
            "token expired",
            "password authentication failed"
        ],
        "Tool Execution Failures": [
            "sonder-log-icu.tool.error.executing.command.log",
            "sonder-log-icu.tool.executor.failed.running.tools.log",
            "Service executor failed to execute successfully: exit status 1"
        ],
        "Certificate Write Failures": [
            "writeAsPem failed",
            "error writing PEM file",
            "failed to decode pem block"
        ],
        "Certificate Errors": [
            "error generating certificates",
            "failed to create cert secret",
            "failed to write certificate file",
            "invalid certificate configuration"
        ],
        "PVC Errors": [
            "PersistentVolumeClaim is not bound",
            "PersistentVolumeClaim is not available",
            "PersistentVolumeClaim is in pending state",
            "PVC pending"
        ],
        "FailedMount Errors": [
            "MountVolume.SetUp failed for volume",
            "references non-existent secret key"
        ],
        "Compute Context Errors": [
            "Compute context to be used by the CAS Formats service",
            "no ready CAS servers, so cas-control is not ready"
        ],
        "Timeouts": [
            "Request timed out",
            "Connection timed out"
        ],
        "PyConfig errors": [
            "Error creating md5sum file"
        ],
        "SAS ESP CSS Errors": [
            "could not find a valid ESP SERVER license"
        ],
        "Bootstrap Errors": [
            "Error bootstrapping resources:",
            "The bootstrap request failed:"
        ],
        "JSON Errors": [
            "JSONDecodeError"
        ],
        "Token Errors": [
            "Failed to obtain dedicated tokens"
        ],
        "Security Constraint Errors": [
            "is forbidden: unable to validate against any security context constraint"
        ],
        "Consul issues": [
            "No cluster leader"
        ],
        "TLS Handshake errors": [
            "http: TLS handshake timeout"
        ],
        "RabbitMQ issues": [
            "Error on AMQP connection",
            "reason: {{badmatch,{error,noproc}},",
            "reason: reached_max_restart_intensity",
            "errorContext: child_terminated",
            "errorContext: shutdown"
        ],
        "Workload Orchestrator issues": [
            "SGMGM_MSG_MANAGER_JOB_KILLED"
        ]
    }
}